bam/__init__.py
bam/wip.py
rham/__init__.py
rham/wip.py
rham-0.0.1.dist-info/METADATA
rham-0.0.1.dist-info/WHEEL
rham-0.0.1.dist-info/top_level.txt
rham-0.0.1.dist-info/RECORD
