Metadata-Version: 2.1
Name: rham
Version: 0.0.1
Summary: Work in progress
Home-page: https://github.com/rhoban/rham/
Author: Rhoban team
Author-email: team@rhoban.com
License: UNKNOWN
Keywords: robot robotics
Platform: UNKNOWN
Classifier: Programming Language :: Python :: 3
Classifier: License :: OSI Approved :: MIT License
Classifier: Operating System :: OS Independent
Requires-Python: >=3.6
Requires-Dist: numpy
